midori/__init__.py
midori/core.py
midori/plugins/base.py
midori/plugins/example_plugins.py
midori/plugins/helpers.py
midori/treatments_helper.py
midori-1.0.3.dist-info/METADATA
midori-1.0.3.dist-info/WHEEL
midori-1.0.3.dist-info/RECORD
