Metadata-Version: 2.1
Name: midori
Version: 1.0.3
Summary: 🍃 streamline remote software engineering experiments
Author: Xingwen Xiao
Author-email: xingwen.xiao@student.uva.nl
Requires-Python: >=3.12,<4.0
Classifier: Programming Language :: Python :: 3
Classifier: Programming Language :: Python :: 3.12
Requires-Dist: paramiko (>=3.4.0,<4.0.0)
